{
  "config": "{\"version\":\"5.37\",\"themeCollection\":{\"baseTheme\":{\"name\":\"CY20SU09\",\"version\":\"5.15\",\"type\":2},\"customTheme\":{\"name\":\"Frontier\",\"version\":\"5.15\",\"type\":2}},\"activeSectionIndex\":0,\"defaultDrillFilterOtherVisuals\":true,\"linguisticSchemaSyncVersion\":2,\"settings\":{\"useNewFilterPaneExperience\":true,\"allowChangeFilterTypes\":true,\"useStylableVisualContainerHeader\":true,\"exportDataMode\":1,\"filterPaneHiddenInEditMode\":true},\"objects\":{\"section\":[{\"properties\":{\"verticalAlignment\":{\"expr\":{\"Literal\":{\"Value\":\"'Top'\"}}}}}],\"outspacePane\":[{\"properties\":{\"expanded\":{\"expr\":{\"Literal\":{\"Value\":\"false\"}}}}}]}}",
  "layoutOptimization": 0,
  "resourcePackages": [
    {
      "resourcePackage": {
        "disabled": false,
        "items": [
          {
            "name": "choropleth4C77906D867C4C09AFE83BA5E2AA106A.pbiviz.json",
            "path": "choropleth4C77906D867C4C09AFE83BA5E2AA106A.pbiviz.json",
            "type": 5
          }
        ],
        "name": "choropleth4C77906D867C4C09AFE83BA5E2AA106A",
        "type": 0
      }
    },
    {
      "resourcePackage": {
        "disabled": false,
        "items": [
          {
            "name": "ClusteringUsingOPTICSCAD9384DAA1042E78771F55A0BD811D8.pbiviz.json",
            "path": "ClusteringUsingOPTICSCAD9384DAA1042E78771F55A0BD811D8.pbiviz.json",
            "type": 5
          }
        ],
        "name": "ClusteringUsingOPTICSCAD9384DAA1042E78771F55A0BD811D8",
        "type": 0
      }
    },
    {
      "resourcePackage": {
        "disabled": false,
        "items": [
          {
            "name": "ClusterMap1652434605854.pbiviz.json",
            "path": "ClusterMap1652434605854.pbiviz.json",
            "type": 5
          }
        ],
        "name": "ClusterMap1652434605854",
        "type": 0
      }
    },
    {
      "resourcePackage": {
        "disabled": false,
        "items": [
          {
            "name": "CY20SU09",
            "path": "BaseThemes/CY20SU09.json",
            "type": 202
          },
          {
            "name": "Frontier",
            "path": "BuiltInThemes/Frontier.json",
            "type": 201
          }
        ],
        "name": "SharedResources",
        "type": 2
      }
    },
    {
      "resourcePackage": {
        "disabled": false,
        "items": [
          {
            "name": "drilldownCartogramD5E1077C70074FFCB26AFC2A636614BF.pbiviz.json",
            "path": "drilldownCartogramD5E1077C70074FFCB26AFC2A636614BF.pbiviz.json",
            "type": 5
          }
        ],
        "name": "drilldownCartogramD5E1077C70074FFCB26AFC2A636614BF",
        "type": 0
      }
    },
    {
      "resourcePackage": {
        "disabled": false,
        "items": [
          {
            "name": "EnhancedScatterChart1443994985041.pbiviz.json",
            "path": "EnhancedScatterChart1443994985041.pbiviz.json",
            "type": 5
          }
        ],
        "name": "EnhancedScatterChart1443994985041",
        "type": 0
      }
    },
    {
      "resourcePackage": {
        "disabled": false,
        "items": [
          {
            "name": "ForceGraph1449359463895.pbiviz.json",
            "path": "ForceGraph1449359463895.pbiviz.json",
            "type": 5
          }
        ],
        "name": "ForceGraph1449359463895",
        "type": 0
      }
    },
    {
      "resourcePackage": {
        "disabled": false,
        "items": [
          {
            "name": "GlobeMap1447669447625.pbiviz.json",
            "path": "GlobeMap1447669447625.pbiviz.json",
            "type": 5
          }
        ],
        "name": "GlobeMap1447669447625",
        "type": 0
      }
    },
    {
      "resourcePackage": {
        "disabled": false,
        "items": [
          {
            "name": "heatmapF244EA9EE1F34E828A80CF19B41976F8.pbiviz.json",
            "path": "heatmapF244EA9EE1F34E828A80CF19B41976F8.pbiviz.json",
            "type": 5
          }
        ],
        "name": "heatmapF244EA9EE1F34E828A80CF19B41976F8",
        "type": 0
      }
    },
    {
      "resourcePackage": {
        "disabled": false,
        "items": [
          {
            "name": "HorizontalFunnel1449177164235.pbiviz.json",
            "path": "HorizontalFunnel1449177164235.pbiviz.json",
            "type": 5
          }
        ],
        "name": "HorizontalFunnel1449177164235",
        "type": 0
      }
    },
    {
      "resourcePackage": {
        "disabled": false,
        "items": [
          {
            "name": "LineDotChart1460463831201.pbiviz.json",
            "path": "LineDotChart1460463831201.pbiviz.json",
            "type": 5
          }
        ],
        "name": "LineDotChart1460463831201",
        "type": 0
      }
    },
    {
      "resourcePackage": {
        "disabled": false,
        "items": [
          {
            "name": "MekkoChart1449744733038.pbiviz.json",
            "path": "MekkoChart1449744733038.pbiviz.json",
            "type": 5
          }
        ],
        "name": "MekkoChart1449744733038",
        "type": 0
      }
    },
    {
      "resourcePackage": {
        "disabled": false,
        "items": [
          {
            "name": "multiInfoCards9D184BB3D4E44A139DA08142D76EFD36.pbiviz.json",
            "path": "multiInfoCards9D184BB3D4E44A139DA08142D76EFD36.pbiviz.json",
            "type": 5
          }
        ],
        "name": "multiInfoCards9D184BB3D4E44A139DA08142D76EFD36",
        "type": 0
      }
    },
    {
      "resourcePackage": {
        "disabled": false,
        "items": [
          {
            "name": "PBI_CV_3EEA6E26_A754_4ECA_BE51_C93859851FB2.pbiviz.json",
            "path": "PBI_CV_3EEA6E26_A754_4ECA_BE51_C93859851FB2.pbiviz.json",
            "type": 5
          }
        ],
        "name": "PBI_CV_3EEA6E26_A754_4ECA_BE51_C93859851FB2",
        "type": 0
      }
    },
    {
      "resourcePackage": {
        "disabled": false,
        "items": [
          {
            "name": "PBI_CV_73744D90_4DC9_4F18_8BA5_EE8FA5C98035.pbiviz.json",
            "path": "PBI_CV_73744D90_4DC9_4F18_8BA5_EE8FA5C98035.pbiviz.json",
            "type": 5
          }
        ],
        "name": "PBI_CV_73744D90_4DC9_4F18_8BA5_EE8FA5C98035",
        "type": 0
      }
    },
    {
      "resourcePackage": {
        "disabled": false,
        "items": [
          {
            "name": "PBI_CV_967A08ED_59CD_405F_B41A_8CE2050AD30E.pbiviz.json",
            "path": "PBI_CV_967A08ED_59CD_405F_B41A_8CE2050AD30E.pbiviz.json",
            "type": 5
          }
        ],
        "name": "PBI_CV_967A08ED_59CD_405F_B41A_8CE2050AD30E",
        "type": 0
      }
    },
    {
      "resourcePackage": {
        "disabled": false,
        "items": [
          {
            "name": "PBI_CV_9D783E0D_2610_4C22_9576_88AD092AB59E.pbiviz.json",
            "path": "PBI_CV_9D783E0D_2610_4C22_9576_88AD092AB59E.pbiviz.json",
            "type": 5
          }
        ],
        "name": "PBI_CV_9D783E0D_2610_4C22_9576_88AD092AB59E",
        "type": 0
      }
    },
    {
      "resourcePackage": {
        "disabled": false,
        "items": [
          {
            "name": "PBI_CV_AD348DC9_41C4_4867_B19O_53F9RDC6IEAS_HTML.pbiviz.json",
            "path": "PBI_CV_AD348DC9_41C4_4867_B19O_53F9RDC6IEAS_HTML.pbiviz.json",
            "type": 5
          }
        ],
        "name": "PBI_CV_AD348DC9_41C4_4867_B19O_53F9RDC6IEAS_HTML",
        "type": 0
      }
    },
    {
      "resourcePackage": {
        "disabled": false,
        "items": [
          {
            "name": "PBI_CV_EB3A4088_75C5_4746_9D8B_255A7B7ECD6C.pbiviz.json",
            "path": "PBI_CV_EB3A4088_75C5_4746_9D8B_255A7B7ECD6C.pbiviz.json",
            "type": 5
          }
        ],
        "name": "PBI_CV_EB3A4088_75C5_4746_9D8B_255A7B7ECD6C",
        "type": 0
      }
    },
    {
      "resourcePackage": {
        "disabled": false,
        "items": [
          {
            "name": "RadarChart1446119667547.pbiviz.json",
            "path": "RadarChart1446119667547.pbiviz.json",
            "type": 5
          }
        ],
        "name": "RadarChart1446119667547",
        "type": 0
      }
    },
    {
      "resourcePackage": {
        "disabled": false,
        "items": [
          {
            "name": "radarChart5F59D098BB90499F8C33EBEBCEE4FEBF.pbiviz.json",
            "path": "radarChart5F59D098BB90499F8C33EBEBCEE4FEBF.pbiviz.json",
            "type": 5
          }
        ],
        "name": "radarChart5F59D098BB90499F8C33EBEBCEE4FEBF",
        "type": 0
      }
    },
    {
      "resourcePackage": {
        "disabled": false,
        "items": [
          {
            "name": "sankey02300D1BE6F5427989F3DE31CCA9E0F32020.pbiviz.json",
            "path": "sankey02300D1BE6F5427989F3DE31CCA9E0F32020.pbiviz.json",
            "type": 5
          }
        ],
        "name": "sankey02300D1BE6F5427989F3DE31CCA9E0F32020",
        "type": 0
      }
    },
    {
      "resourcePackage": {
        "disabled": false,
        "items": [
          {
            "name": "socialNetworkGraph99E9F31DDFD7429BACA50118466E4D11.pbiviz.json",
            "path": "socialNetworkGraph99E9F31DDFD7429BACA50118466E4D11.pbiviz.json",
            "type": 5
          }
        ],
        "name": "socialNetworkGraph99E9F31DDFD7429BACA50118466E4D11",
        "type": 0
      }
    },
    {
      "resourcePackage": {
        "disabled": false,
        "items": [
          {
            "name": "summaryTableEBA1E7D9C77B47D0914D7D98B4D120DC.pbiviz.json",
            "path": "summaryTableEBA1E7D9C77B47D0914D7D98B4D120DC.pbiviz.json",
            "type": 5
          }
        ],
        "name": "summaryTableEBA1E7D9C77B47D0914D7D98B4D120DC",
        "type": 0
      }
    },
    {
      "resourcePackage": {
        "disabled": false,
        "items": [
          {
            "name": "threejsE0E480FFE18F46FE90AD2FA3A0D80C5F.pbiviz.json",
            "path": "threejsE0E480FFE18F46FE90AD2FA3A0D80C5F.pbiviz.json",
            "type": 5
          }
        ],
        "name": "threejsE0E480FFE18F46FE90AD2FA3A0D80C5F",
        "type": 0
      }
    },
    {
      "resourcePackage": {
        "disabled": false,
        "items": [
          {
            "name": "TimelineStoryteller1652434605730.pbiviz.json",
            "path": "TimelineStoryteller1652434605730.pbiviz.json",
            "type": 5
          }
        ],
        "name": "TimelineStoryteller1652434605730",
        "type": 0
      }
    },
    {
      "resourcePackage": {
        "disabled": false,
        "items": [
          {
            "name": "vennDiagram8527AJ74DB74562488PCR752UTY9465.pbiviz.json",
            "path": "vennDiagram8527AJ74DB74562488PCR752UTY9465.pbiviz.json",
            "type": 5
          }
        ],
        "name": "vennDiagram8527AJ74DB74562488PCR752UTY9465",
        "type": 0
      }
    },
    {
      "resourcePackage": {
        "disabled": false,
        "items": [
          {
            "name": "WordCloud1447959067750.pbiviz.json",
            "path": "WordCloud1447959067750.pbiviz.json",
            "type": 5
          }
        ],
        "name": "WordCloud1447959067750",
        "type": 0
      }
    }
  ],
  "sections": [
    {
      "config": "{\"objects\":{\"filterCard\":[{\"properties\":{\"backgroundColor\":{\"solid\":{\"color\":{\"expr\":{\"Literal\":{\"Value\":\"'#070f25'\"}}}}}},\"selector\":{\"id\":\"Available\"}}],\"outspacePane\":[{\"properties\":{\"backgroundColor\":{\"solid\":{\"color\":{\"expr\":{\"ThemeDataColor\":{\"ColorId\":1,\"Percent\":0}}}}}}}]}}",
      "displayName": "Página 1",
      "displayOption": 1,
      "filters": "[]",
      "height": 720.00,
      "name": "ReportSection",
      "visualContainers": [
        {
          "config": "{\"name\":\"0d812c41a7071941b6b1\",\"layouts\":[{\"id\":0,\"position\":{\"x\":528,\"y\":160,\"z\":1000,\"width\":736,\"height\":352,\"tabOrder\":0}}],\"singleVisual\":{\"visualType\":\"map\",\"projections\":{\"Category\":[{\"queryRef\":\"Municipal-Delitos-2015-2021_dic2021.mun_edo_pais\",\"active\":true}],\"Size\":[{\"queryRef\":\"Sum(Municipal-Delitos-2015-2021_dic2021.delitos)\"}],\"Series\":[{\"queryRef\":\"Municipal-Delitos-2015-2021_dic2021.Entidad\"}]},\"prototypeQuery\":{\"Version\":2,\"From\":[{\"Name\":\"m\",\"Entity\":\"Municipal-Delitos-2015-2021_dic2021\",\"Type\":0}],\"Select\":[{\"Column\":{\"Expression\":{\"SourceRef\":{\"Source\":\"m\"}},\"Property\":\"mun_edo_pais\"},\"Name\":\"Municipal-Delitos-2015-2021_dic2021.mun_edo_pais\"},{\"Aggregation\":{\"Expression\":{\"Column\":{\"Expression\":{\"SourceRef\":{\"Source\":\"m\"}},\"Property\":\"delitos\"}},\"Function\":0},\"Name\":\"Sum(Municipal-Delitos-2015-2021_dic2021.delitos)\"},{\"Column\":{\"Expression\":{\"SourceRef\":{\"Source\":\"m\"}},\"Property\":\"Entidad\"},\"Name\":\"Municipal-Delitos-2015-2021_dic2021.Entidad\"}],\"OrderBy\":[{\"Direction\":2,\"Expression\":{\"Aggregation\":{\"Expression\":{\"Column\":{\"Expression\":{\"SourceRef\":{\"Source\":\"m\"}},\"Property\":\"delitos\"}},\"Function\":0}}}]},\"drillFilterOtherVisuals\":true,\"hasDefaultSort\":true,\"objects\":{\"bubbles\":[{\"properties\":{\"bubbleSize\":{\"expr\":{\"Literal\":{\"Value\":\"28L\"}}}}}],\"mapControls\":[{\"properties\":{\"showZoomButtons\":{\"expr\":{\"Literal\":{\"Value\":\"true\"}}}}}],\"mapStyles\":[{\"properties\":{\"mapTheme\":{\"expr\":{\"Literal\":{\"Value\":\"'canvasDark'\"}}}}}],\"legend\":[{\"properties\":{\"show\":{\"expr\":{\"Literal\":{\"Value\":\"false\"}}},\"fontSize\":{\"expr\":{\"Literal\":{\"Value\":\"9D\"}}}}}]},\"vcObjects\":{\"border\":[{\"properties\":{\"show\":{\"expr\":{\"Literal\":{\"Value\":\"false\"}}},\"color\":{\"solid\":{\"color\":{\"expr\":{\"ThemeDataColor\":{\"ColorId\":1,\"Percent\":0}}}}},\"radius\":{\"expr\":{\"Literal\":{\"Value\":\"22D\"}}}}}],\"background\":[{\"properties\":{\"show\":{\"expr\":{\"Literal\":{\"Value\":\"false\"}}},\"color\":{\"solid\":{\"color\":{\"expr\":{\"Literal\":{\"Value\":\"'#070f25'\"}}}}},\"transparency\":{\"expr\":{\"Literal\":{\"Value\":\"49D\"}}}}}],\"stylePreset\":[{\"properties\":{\"name\":{\"expr\":{\"Literal\":{\"Value\":\"'BoldHeader'\"}}}}}],\"dropShadow\":[{\"properties\":{\"show\":{\"expr\":{\"Literal\":{\"Value\":\"false\"}}},\"preset\":{\"expr\":{\"Literal\":{\"Value\":\"'Center'\"}}},\"position\":{\"expr\":{\"Literal\":{\"Value\":\"'Inner'\"}}},\"color\":{\"solid\":{\"color\":{\"expr\":{\"ThemeDataColor\":{\"ColorId\":0,\"Percent\":-0.6}}}}},\"transparency\":{\"expr\":{\"Literal\":{\"Value\":\"70L\"}}},\"shadowSpread\":{\"expr\":{\"Literal\":{\"Value\":\"0L\"}}},\"shadowBlur\":{\"expr\":{\"Literal\":{\"Value\":\"20L\"}}},\"angle\":{\"expr\":{\"Literal\":{\"Value\":\"0L\"}}},\"shadowDistance\":{\"expr\":{\"Literal\":{\"Value\":\"0L\"}}}}}],\"title\":[{\"properties\":{\"text\":{\"expr\":{\"Literal\":{\"Value\":\"'Por municipio'\"}}},\"show\":{\"expr\":{\"Literal\":{\"Value\":\"true\"}}},\"fontColor\":{\"solid\":{\"color\":{\"expr\":{\"Literal\":{\"Value\":\"'#ffffff'\"}}}}},\"background\":{\"solid\":{\"color\":{\"expr\":{\"Literal\":{\"Value\":\"'#070f25'\"}}}}},\"alignment\":{\"expr\":{\"Literal\":{\"Value\":\"'center'\"}}},\"fontSize\":{\"expr\":{\"Literal\":{\"Value\":\"11D\"}}},\"fontFamily\":{\"expr\":{\"Literal\":{\"Value\":\"'''Segoe UI Bold'', wf_segoe-ui_bold, helvetica, arial, sans-serif'\"}}}}}]}}}",
          "filters": "[]",
          "height": 352.00,
          "width": 736.00,
          "x": 528.00,
          "y": 160.00,
          "z": 1000.00
        },
        {
          "config": "{\"name\":\"3e4917bda340e4828ded\",\"layouts\":[{\"id\":0,\"position\":{\"x\":48,\"y\":16,\"z\":7000,\"width\":384,\"height\":128,\"tabOrder\":6000}}],\"singleVisual\":{\"visualType\":\"textbox\",\"drillFilterOtherVisuals\":true,\"objects\":{\"general\":[{\"properties\":{\"paragraphs\":[{\"textRuns\":[{\"value\":\"\"}],\"horizontalTextAlignment\":\"center\"},{\"textRuns\":[{\"value\":\"INCIDENCIA DELICTIVA\",\"textStyle\":{\"fontWeight\":\"bold\",\"fontSize\":\"24pt\",\"color\":\"#070f25\"}}],\"horizontalTextAlignment\":\"center\"},{\"textRuns\":[{\"value\":\"DELITOS POR MUNICIPIO\",\"textStyle\":{\"fontSize\":\"12pt\",\"color\":\"#070f25\"}}],\"horizontalTextAlignment\":\"center\"}]}}]}}}",
          "filters": "[]",
          "height": 128.00,
          "width": 384.00,
          "x": 48.00,
          "y": 16.00,
          "z": 7000.00
        },
        {
          "config": "{\"name\":\"533680041070c927130c\",\"layouts\":[{\"id\":0,\"position\":{\"x\":480,\"y\":80,\"z\":5000,\"width\":640,\"height\":64,\"tabOrder\":4000}}],\"singleVisual\":{\"visualType\":\"slicer\",\"projections\":{\"Values\":[{\"queryRef\":\"Municipal-Delitos-2015-2021_dic2021.Año\",\"active\":true}]},\"prototypeQuery\":{\"Version\":2,\"From\":[{\"Name\":\"m\",\"Entity\":\"Municipal-Delitos-2015-2021_dic2021\",\"Type\":0}],\"Select\":[{\"Column\":{\"Expression\":{\"SourceRef\":{\"Source\":\"m\"}},\"Property\":\"Año\"},\"Name\":\"Municipal-Delitos-2015-2021_dic2021.Año\"}]},\"drillFilterOtherVisuals\":true,\"objects\":{\"data\":[{\"properties\":{\"mode\":{\"expr\":{\"Literal\":{\"Value\":\"'Basic'\"}}}}}],\"general\":[{\"properties\":{\"outlineColor\":{\"solid\":{\"color\":{\"expr\":{\"ThemeDataColor\":{\"ColorId\":3,\"Percent\":-0.5}}}}},\"orientation\":{\"expr\":{\"Literal\":{\"Value\":\"1D\"}}}}}],\"header\":[{\"properties\":{\"show\":{\"expr\":{\"Literal\":{\"Value\":\"true\"}}},\"fontColor\":{\"solid\":{\"color\":{\"expr\":{\"Literal\":{\"Value\":\"'#070f25'\"}}}}},\"textSize\":{\"expr\":{\"Literal\":{\"Value\":\"9D\"}}},\"fontFamily\":{\"expr\":{\"Literal\":{\"Value\":\"'''Segoe UI Bold'', wf_segoe-ui_bold, helvetica, arial, sans-serif'\"}}},\"outlineStyle\":{\"expr\":{\"Literal\":{\"Value\":\"0L\"}}}}}],\"items\":[{\"properties\":{\"fontColor\":{\"solid\":{\"color\":{\"expr\":{\"ThemeDataColor\":{\"ColorId\":0,\"Percent\":0}}}}},\"background\":{\"solid\":{\"color\":{\"expr\":{\"ThemeDataColor\":{\"ColorId\":3,\"Percent\":-0.5}}}}}}}]},\"vcObjects\":{\"background\":[{\"properties\":{\"show\":{\"expr\":{\"Literal\":{\"Value\":\"false\"}}},\"color\":{\"solid\":{\"color\":{\"expr\":{\"ThemeDataColor\":{\"ColorId\":1,\"Percent\":0}}}}},\"transparency\":{\"expr\":{\"Literal\":{\"Value\":\"49D\"}}}}}],\"border\":[{\"properties\":{\"show\":{\"expr\":{\"Literal\":{\"Value\":\"false\"}}},\"color\":{\"solid\":{\"color\":{\"expr\":{\"ThemeDataColor\":{\"ColorId\":1,\"Percent\":0}}}}},\"radius\":{\"expr\":{\"Literal\":{\"Value\":\"22D\"}}}}}],\"dropShadow\":[{\"properties\":{\"show\":{\"expr\":{\"Literal\":{\"Value\":\"false\"}}},\"preset\":{\"expr\":{\"Literal\":{\"Value\":\"'Center'\"}}},\"position\":{\"expr\":{\"Literal\":{\"Value\":\"'Inner'\"}}},\"color\":{\"solid\":{\"color\":{\"expr\":{\"Literal\":{\"Value\":\"'#666666'\"}}}}},\"transparency\":{\"expr\":{\"Literal\":{\"Value\":\"70L\"}}},\"shadowSpread\":{\"expr\":{\"Literal\":{\"Value\":\"0L\"}}},\"shadowBlur\":{\"expr\":{\"Literal\":{\"Value\":\"20L\"}}},\"angle\":{\"expr\":{\"Literal\":{\"Value\":\"0L\"}}},\"shadowDistance\":{\"expr\":{\"Literal\":{\"Value\":\"0L\"}}}}}],\"stylePreset\":[{\"properties\":{\"name\":{\"expr\":{\"Literal\":{\"Value\":\"'Minimal'\"}}}}}],\"title\":[{\"properties\":{\"show\":{\"expr\":{\"Literal\":{\"Value\":\"false\"}}}}}]}}}",
          "filters": "[{\"expression\":{\"Column\":{\"Expression\":{\"SourceRef\":{\"Entity\":\"Municipal-Delitos-2015-2021_dic2021\"}},\"Property\":\"Año\"}},\"filter\":{\"Version\":2,\"From\":[{\"Name\":\"m\",\"Entity\":\"Municipal-Delitos-2015-2021_dic2021\",\"Type\":0}],\"Where\":[{\"Condition\":{\"Comparison\":{\"ComparisonKind\":2,\"Left\":{\"Column\":{\"Expression\":{\"SourceRef\":{\"Source\":\"m\"}},\"Property\":\"Año\"}},\"Right\":{\"Literal\":{\"Value\":\"2018L\"}}}}}]},\"type\":\"Advanced\",\"howCreated\":0,\"isHiddenInViewMode\":false}]",
          "height": 64.00,
          "width": 640.00,
          "x": 480.00,
          "y": 80.00,
          "z": 5000.00
        },
        {
          "config": "{\"name\":\"5479fa1b1d10a6bb2690\",\"layouts\":[{\"id\":0,\"position\":{\"x\":480,\"y\":16,\"z\":8000,\"width\":496,\"height\":64,\"tabOrder\":7000}}],\"singleVisual\":{\"visualType\":\"slicer\",\"projections\":{\"Values\":[{\"queryRef\":\"Municipal-Delitos-2015-2021_dic2021.Incidencia delictiva\",\"active\":true}]},\"prototypeQuery\":{\"Version\":2,\"From\":[{\"Name\":\"m\",\"Entity\":\"Municipal-Delitos-2015-2021_dic2021\",\"Type\":0}],\"Select\":[{\"Column\":{\"Expression\":{\"SourceRef\":{\"Source\":\"m\"}},\"Property\":\"Incidencia delictiva\"},\"Name\":\"Municipal-Delitos-2015-2021_dic2021.Incidencia delictiva\"}]},\"columnProperties\":{\"Municipal-Delitos-2015-2021_dic2021.Incidencia delictiva\":{\"displayName\":\"Incidencia delictiva (no. Delitos)\"}},\"drillFilterOtherVisuals\":true,\"objects\":{\"data\":[{\"properties\":{\"mode\":{\"expr\":{\"Literal\":{\"Value\":\"'Basic'\"}}}}}],\"general\":[{\"properties\":{\"outlineColor\":{\"solid\":{\"color\":{\"expr\":{\"ThemeDataColor\":{\"ColorId\":3,\"Percent\":-0.5}}}}},\"orientation\":{\"expr\":{\"Literal\":{\"Value\":\"1D\"}}}}}],\"items\":[{\"properties\":{\"fontColor\":{\"solid\":{\"color\":{\"expr\":{\"ThemeDataColor\":{\"ColorId\":0,\"Percent\":0}}}}},\"background\":{\"solid\":{\"color\":{\"expr\":{\"ThemeDataColor\":{\"ColorId\":3,\"Percent\":-0.5}}}}}}}],\"header\":[{\"properties\":{\"show\":{\"expr\":{\"Literal\":{\"Value\":\"true\"}}},\"fontColor\":{\"solid\":{\"color\":{\"expr\":{\"Literal\":{\"Value\":\"'#070f25'\"}}}}},\"textSize\":{\"expr\":{\"Literal\":{\"Value\":\"9D\"}}},\"fontFamily\":{\"expr\":{\"Literal\":{\"Value\":\"'''Segoe UI Bold'', wf_segoe-ui_bold, helvetica, arial, sans-serif'\"}}},\"outlineStyle\":{\"expr\":{\"Literal\":{\"Value\":\"0L\"}}}}}]},\"vcObjects\":{\"background\":[{\"properties\":{\"show\":{\"expr\":{\"Literal\":{\"Value\":\"false\"}}},\"color\":{\"solid\":{\"color\":{\"expr\":{\"ThemeDataColor\":{\"ColorId\":1,\"Percent\":0}}}}},\"transparency\":{\"expr\":{\"Literal\":{\"Value\":\"49D\"}}}}}],\"border\":[{\"properties\":{\"show\":{\"expr\":{\"Literal\":{\"Value\":\"false\"}}},\"color\":{\"solid\":{\"color\":{\"expr\":{\"ThemeDataColor\":{\"ColorId\":1,\"Percent\":0}}}}},\"radius\":{\"expr\":{\"Literal\":{\"Value\":\"22D\"}}}}}],\"dropShadow\":[{\"properties\":{\"show\":{\"expr\":{\"Literal\":{\"Value\":\"false\"}}},\"preset\":{\"expr\":{\"Literal\":{\"Value\":\"'Center'\"}}},\"position\":{\"expr\":{\"Literal\":{\"Value\":\"'Inner'\"}}},\"color\":{\"solid\":{\"color\":{\"expr\":{\"Literal\":{\"Value\":\"'#666666'\"}}}}},\"transparency\":{\"expr\":{\"Literal\":{\"Value\":\"70L\"}}},\"shadowSpread\":{\"expr\":{\"Literal\":{\"Value\":\"0L\"}}},\"shadowBlur\":{\"expr\":{\"Literal\":{\"Value\":\"20L\"}}},\"angle\":{\"expr\":{\"Literal\":{\"Value\":\"0L\"}}},\"shadowDistance\":{\"expr\":{\"Literal\":{\"Value\":\"0L\"}}}}}],\"stylePreset\":[{\"properties\":{\"name\":{\"expr\":{\"Literal\":{\"Value\":\"'Minimal'\"}}}}}],\"title\":[{\"properties\":{\"show\":{\"expr\":{\"Literal\":{\"Value\":\"false\"}}}}}]}}}",
          "filters": "[{\"expression\":{\"Column\":{\"Expression\":{\"SourceRef\":{\"Entity\":\"Municipal-Delitos-2015-2021_dic2021\"}},\"Property\":\"Año\"}},\"filter\":{\"Version\":2,\"From\":[{\"Name\":\"m\",\"Entity\":\"Municipal-Delitos-2015-2021_dic2021\",\"Type\":0}],\"Where\":[{\"Condition\":{\"Comparison\":{\"ComparisonKind\":2,\"Left\":{\"Column\":{\"Expression\":{\"SourceRef\":{\"Source\":\"m\"}},\"Property\":\"Año\"}},\"Right\":{\"Literal\":{\"Value\":\"2018L\"}}}}}]},\"type\":\"Advanced\",\"howCreated\":1,\"isHiddenInViewMode\":false}]",
          "height": 64.00,
          "width": 496.00,
          "x": 480.00,
          "y": 16.00,
          "z": 8000.00
        },
        {
          "config": "{\"name\":\"55acae72b2756344d52d\",\"layouts\":[{\"id\":0,\"position\":{\"x\":528,\"y\":528,\"z\":2000,\"width\":736,\"height\":176,\"tabOrder\":1000}}],\"singleVisual\":{\"visualType\":\"treemap\",\"projections\":{\"Group\":[{\"queryRef\":\"Concentrado municipal.Entidad federativa\",\"active\":true}],\"Values\":[{\"queryRef\":\"Sum(Municipal-Delitos-2015-2021_dic2021.delitos)\"}]},\"prototypeQuery\":{\"Version\":2,\"From\":[{\"Name\":\"m\",\"Entity\":\"Municipal-Delitos-2015-2021_dic2021\",\"Type\":0},{\"Name\":\"c\",\"Entity\":\"Concentrado municipal\",\"Type\":0}],\"Select\":[{\"Column\":{\"Expression\":{\"SourceRef\":{\"Source\":\"c\"}},\"Property\":\"Entidad federativa\"},\"Name\":\"Concentrado municipal.Entidad federativa\"},{\"Aggregation\":{\"Expression\":{\"Column\":{\"Expression\":{\"SourceRef\":{\"Source\":\"m\"}},\"Property\":\"delitos\"}},\"Function\":0},\"Name\":\"Sum(Municipal-Delitos-2015-2021_dic2021.delitos)\"}],\"OrderBy\":[{\"Direction\":2,\"Expression\":{\"Aggregation\":{\"Expression\":{\"Column\":{\"Expression\":{\"SourceRef\":{\"Source\":\"m\"}},\"Property\":\"delitos\"}},\"Function\":0}}}]},\"drillFilterOtherVisuals\":true,\"hasDefaultSort\":true,\"objects\":{\"labels\":[{\"properties\":{\"color\":{\"solid\":{\"color\":{\"expr\":{\"Literal\":{\"Value\":\"'#070f25'\"}}}}}}}]},\"vcObjects\":{\"border\":[{\"properties\":{\"show\":{\"expr\":{\"Literal\":{\"Value\":\"false\"}}},\"color\":{\"solid\":{\"color\":{\"expr\":{\"ThemeDataColor\":{\"ColorId\":1,\"Percent\":0}}}}},\"radius\":{\"expr\":{\"Literal\":{\"Value\":\"22D\"}}}}}],\"stylePreset\":[{\"properties\":{\"name\":{\"expr\":{\"Literal\":{\"Value\":\"'BoldHeader'\"}}}}}],\"background\":[{\"properties\":{\"show\":{\"expr\":{\"Literal\":{\"Value\":\"false\"}}},\"color\":{\"solid\":{\"color\":{\"expr\":{\"Literal\":{\"Value\":\"'#070f25'\"}}}}},\"transparency\":{\"expr\":{\"Literal\":{\"Value\":\"49D\"}}}}}],\"dropShadow\":[{\"properties\":{\"show\":{\"expr\":{\"Literal\":{\"Value\":\"false\"}}},\"preset\":{\"expr\":{\"Literal\":{\"Value\":\"'Center'\"}}},\"position\":{\"expr\":{\"Literal\":{\"Value\":\"'Inner'\"}}},\"color\":{\"solid\":{\"color\":{\"expr\":{\"ThemeDataColor\":{\"ColorId\":0,\"Percent\":-0.6}}}}},\"transparency\":{\"expr\":{\"Literal\":{\"Value\":\"70L\"}}},\"shadowSpread\":{\"expr\":{\"Literal\":{\"Value\":\"0L\"}}},\"shadowBlur\":{\"expr\":{\"Literal\":{\"Value\":\"20L\"}}},\"angle\":{\"expr\":{\"Literal\":{\"Value\":\"0L\"}}},\"shadowDistance\":{\"expr\":{\"Literal\":{\"Value\":\"0L\"}}}}}],\"title\":[{\"properties\":{\"text\":{\"expr\":{\"Literal\":{\"Value\":\"'Por estado'\"}}},\"show\":{\"expr\":{\"Literal\":{\"Value\":\"true\"}}},\"fontColor\":{\"solid\":{\"color\":{\"expr\":{\"Literal\":{\"Value\":\"'#ffffff'\"}}}}},\"background\":{\"solid\":{\"color\":{\"expr\":{\"Literal\":{\"Value\":\"'#070f25'\"}}}}},\"alignment\":{\"expr\":{\"Literal\":{\"Value\":\"'center'\"}}},\"fontSize\":{\"expr\":{\"Literal\":{\"Value\":\"11D\"}}},\"fontFamily\":{\"expr\":{\"Literal\":{\"Value\":\"'''Segoe UI Bold'', wf_segoe-ui_bold, helvetica, arial, sans-serif'\"}}}}}]}}}",
          "filters": "[]",
          "height": 176.00,
          "width": 736.00,
          "x": 528.00,
          "y": 528.00,
          "z": 2000.00
        },
        {
          "config": "{\"name\":\"676005f0d8ac3af5c39b\",\"layouts\":[{\"id\":0,\"position\":{\"x\":1104,\"y\":16,\"z\":9000,\"width\":160,\"height\":64,\"tabOrder\":8000}}],\"singleVisual\":{\"visualType\":\"slicer\",\"projections\":{\"Values\":[{\"queryRef\":\"Municipal-Delitos-2015-2021_dic2021.Entidad\",\"active\":true}]},\"prototypeQuery\":{\"Version\":2,\"From\":[{\"Name\":\"m\",\"Entity\":\"Municipal-Delitos-2015-2021_dic2021\",\"Type\":0}],\"Select\":[{\"Column\":{\"Expression\":{\"SourceRef\":{\"Source\":\"m\"}},\"Property\":\"Entidad\"},\"Name\":\"Municipal-Delitos-2015-2021_dic2021.Entidad\"}]},\"drillFilterOtherVisuals\":true,\"objects\":{\"data\":[{\"properties\":{\"mode\":{\"expr\":{\"Literal\":{\"Value\":\"'Dropdown'\"}}}}}],\"general\":[{\"properties\":{\"outlineColor\":{\"solid\":{\"color\":{\"expr\":{\"ThemeDataColor\":{\"ColorId\":3,\"Percent\":-0.5}}}}},\"orientation\":{\"expr\":{\"Literal\":{\"Value\":\"1D\"}}}}}],\"header\":[{\"properties\":{\"show\":{\"expr\":{\"Literal\":{\"Value\":\"true\"}}},\"fontColor\":{\"solid\":{\"color\":{\"expr\":{\"Literal\":{\"Value\":\"'#070f25'\"}}}}},\"textSize\":{\"expr\":{\"Literal\":{\"Value\":\"9D\"}}},\"fontFamily\":{\"expr\":{\"Literal\":{\"Value\":\"'''Segoe UI Bold'', wf_segoe-ui_bold, helvetica, arial, sans-serif'\"}}},\"outlineStyle\":{\"expr\":{\"Literal\":{\"Value\":\"0L\"}}}}}],\"items\":[{\"properties\":{\"fontColor\":{\"solid\":{\"color\":{\"expr\":{\"ThemeDataColor\":{\"ColorId\":0,\"Percent\":0}}}}},\"background\":{\"solid\":{\"color\":{\"expr\":{\"ThemeDataColor\":{\"ColorId\":3,\"Percent\":-0.5}}}}}}}]},\"vcObjects\":{\"background\":[{\"properties\":{\"show\":{\"expr\":{\"Literal\":{\"Value\":\"false\"}}},\"color\":{\"solid\":{\"color\":{\"expr\":{\"ThemeDataColor\":{\"ColorId\":1,\"Percent\":0}}}}},\"transparency\":{\"expr\":{\"Literal\":{\"Value\":\"49D\"}}}}}],\"border\":[{\"properties\":{\"show\":{\"expr\":{\"Literal\":{\"Value\":\"false\"}}},\"color\":{\"solid\":{\"color\":{\"expr\":{\"ThemeDataColor\":{\"ColorId\":1,\"Percent\":0}}}}},\"radius\":{\"expr\":{\"Literal\":{\"Value\":\"22D\"}}}}}],\"dropShadow\":[{\"properties\":{\"show\":{\"expr\":{\"Literal\":{\"Value\":\"false\"}}},\"preset\":{\"expr\":{\"Literal\":{\"Value\":\"'Center'\"}}},\"position\":{\"expr\":{\"Literal\":{\"Value\":\"'Inner'\"}}},\"color\":{\"solid\":{\"color\":{\"expr\":{\"Literal\":{\"Value\":\"'#666666'\"}}}}},\"transparency\":{\"expr\":{\"Literal\":{\"Value\":\"70L\"}}},\"shadowSpread\":{\"expr\":{\"Literal\":{\"Value\":\"0L\"}}},\"shadowBlur\":{\"expr\":{\"Literal\":{\"Value\":\"20L\"}}},\"angle\":{\"expr\":{\"Literal\":{\"Value\":\"0L\"}}},\"shadowDistance\":{\"expr\":{\"Literal\":{\"Value\":\"0L\"}}}}}],\"stylePreset\":[{\"properties\":{\"name\":{\"expr\":{\"Literal\":{\"Value\":\"'Minimal'\"}}}}}],\"title\":[{\"properties\":{\"show\":{\"expr\":{\"Literal\":{\"Value\":\"false\"}}}}}]}}}",
          "filters": "[]",
          "height": 64.00,
          "width": 160.00,
          "x": 1104.00,
          "y": 16.00,
          "z": 9000.00
        },
        {
          "config": "{\"name\":\"9666afecf2c817b25640\",\"layouts\":[{\"id\":0,\"position\":{\"x\":16,\"y\":384,\"z\":3000,\"width\":496,\"height\":320,\"tabOrder\":2000}}],\"singleVisual\":{\"visualType\":\"pivotTable\",\"projections\":{\"Values\":[{\"queryRef\":\"Sum(Municipal-Delitos-2015-2021_dic2021.delitos)\"}],\"Columns\":[{\"queryRef\":\"Municipal-Delitos-2015-2021_dic2021.Año\",\"active\":true}],\"Rows\":[{\"queryRef\":\"Municipal-Delitos-2015-2021_dic2021.Tipo de delito\",\"active\":true}]},\"prototypeQuery\":{\"Version\":2,\"From\":[{\"Name\":\"m\",\"Entity\":\"Municipal-Delitos-2015-2021_dic2021\",\"Type\":0}],\"Select\":[{\"Aggregation\":{\"Expression\":{\"Column\":{\"Expression\":{\"SourceRef\":{\"Source\":\"m\"}},\"Property\":\"delitos\"}},\"Function\":0},\"Name\":\"Sum(Municipal-Delitos-2015-2021_dic2021.delitos)\"},{\"Column\":{\"Expression\":{\"SourceRef\":{\"Source\":\"m\"}},\"Property\":\"Año\"},\"Name\":\"Municipal-Delitos-2015-2021_dic2021.Año\"},{\"Column\":{\"Expression\":{\"SourceRef\":{\"Source\":\"m\"}},\"Property\":\"Tipo de delito\"},\"Name\":\"Municipal-Delitos-2015-2021_dic2021.Tipo de delito\"}],\"OrderBy\":[{\"Direction\":2,\"Expression\":{\"Aggregation\":{\"Expression\":{\"Column\":{\"Expression\":{\"SourceRef\":{\"Source\":\"m\"}},\"Property\":\"delitos\"}},\"Function\":0}}}]},\"drillFilterOtherVisuals\":true,\"hasDefaultSort\":true,\"objects\":{\"values\":[{\"properties\":{\"backColor\":{\"solid\":{\"color\":{\"expr\":{\"FillRule\":{\"Input\":{\"Aggregation\":{\"Expression\":{\"Column\":{\"Expression\":{\"SourceRef\":{\"Entity\":\"Municipal-Delitos-2015-2021_dic2021\"}},\"Property\":\"delitos\"}},\"Function\":0}},\"FillRule\":{\"linearGradient2\":{\"min\":{\"color\":{\"Literal\":{\"Value\":\"'#c6dff3'\"}}},\"max\":{\"color\":{\"Literal\":{\"Value\":\"'#395871'\"}}},\"nullColoringStrategy\":{\"strategy\":{\"Literal\":{\"Value\":\"'asZero'\"}}}}}}}}}}},\"selector\":{\"data\":[{\"dataViewWildcard\":{\"matchingOption\":1}}],\"metadata\":\"Sum(Municipal-Delitos-2015-2021_dic2021.delitos)\"}},{\"properties\":{\"fontSize\":{\"expr\":{\"Literal\":{\"Value\":\"8D\"}}}}}],\"columnFormatting\":[{\"properties\":{\"backColor\":{\"solid\":{\"color\":{\"expr\":{\"ThemeDataColor\":{\"ColorId\":3,\"Percent\":0.6}}}}},\"labelDisplayUnits\":{\"expr\":{\"Literal\":{\"Value\":\"1000D\"}}},\"alignment\":{\"expr\":{\"Literal\":{\"Value\":\"'Right'\"}}}},\"selector\":{\"metadata\":\"Sum(Municipal-Delitos-2015-2021_dic2021.delitos)\"}}],\"columnHeaders\":[{\"properties\":{\"alignment\":{\"expr\":{\"Literal\":{\"Value\":\"'Right'\"}}}}}],\"columnWidth\":[{\"properties\":{\"value\":{\"expr\":{\"Literal\":{\"Value\":\"149.4595328625747D\"}}}},\"selector\":{\"metadata\":\"Municipal-Delitos-2015-2021_dic2021.Tipo de delito\"}}],\"rowTotal\":[{\"properties\":{\"backColor\":{\"solid\":{\"color\":{\"expr\":{\"Literal\":{\"Value\":\"'#252c45'\"}}}}},\"fontColor\":{\"solid\":{\"color\":{\"expr\":{\"ThemeDataColor\":{\"ColorId\":0,\"Percent\":0}}}}}}}],\"columnTotal\":[{\"properties\":{\"backColor\":{\"solid\":{\"color\":{\"expr\":{\"Literal\":{\"Value\":\"'#252c45'\"}}}}},\"fontColor\":{\"solid\":{\"color\":{\"expr\":{\"ThemeDataColor\":{\"ColorId\":0,\"Percent\":0}}}}}}}]},\"vcObjects\":{\"stylePreset\":[{\"properties\":{\"name\":{\"expr\":{\"Literal\":{\"Value\":\"'BoldHeader'\"}}}}}],\"border\":[{\"properties\":{\"show\":{\"expr\":{\"Literal\":{\"Value\":\"false\"}}},\"color\":{\"solid\":{\"color\":{\"expr\":{\"ThemeDataColor\":{\"ColorId\":1,\"Percent\":0}}}}},\"radius\":{\"expr\":{\"Literal\":{\"Value\":\"22D\"}}}}}],\"background\":[{\"properties\":{\"show\":{\"expr\":{\"Literal\":{\"Value\":\"false\"}}},\"color\":{\"solid\":{\"color\":{\"expr\":{\"Literal\":{\"Value\":\"'#070f25'\"}}}}},\"transparency\":{\"expr\":{\"Literal\":{\"Value\":\"49D\"}}}}}],\"dropShadow\":[{\"properties\":{\"show\":{\"expr\":{\"Literal\":{\"Value\":\"false\"}}},\"preset\":{\"expr\":{\"Literal\":{\"Value\":\"'Center'\"}}},\"position\":{\"expr\":{\"Literal\":{\"Value\":\"'Inner'\"}}},\"color\":{\"solid\":{\"color\":{\"expr\":{\"ThemeDataColor\":{\"ColorId\":0,\"Percent\":-0.6}}}}},\"transparency\":{\"expr\":{\"Literal\":{\"Value\":\"70L\"}}},\"shadowSpread\":{\"expr\":{\"Literal\":{\"Value\":\"0L\"}}},\"shadowBlur\":{\"expr\":{\"Literal\":{\"Value\":\"20L\"}}},\"angle\":{\"expr\":{\"Literal\":{\"Value\":\"0L\"}}},\"shadowDistance\":{\"expr\":{\"Literal\":{\"Value\":\"0L\"}}}}}],\"title\":[{\"properties\":{\"text\":{\"expr\":{\"Literal\":{\"Value\":\"'Por bien jurídico afectado'\"}}},\"show\":{\"expr\":{\"Literal\":{\"Value\":\"true\"}}},\"fontColor\":{\"solid\":{\"color\":{\"expr\":{\"Literal\":{\"Value\":\"'#ffffff'\"}}}}},\"background\":{\"solid\":{\"color\":{\"expr\":{\"Literal\":{\"Value\":\"'#070f25'\"}}}}},\"alignment\":{\"expr\":{\"Literal\":{\"Value\":\"'center'\"}}},\"fontSize\":{\"expr\":{\"Literal\":{\"Value\":\"11D\"}}},\"fontFamily\":{\"expr\":{\"Literal\":{\"Value\":\"'''Segoe UI Bold'', wf_segoe-ui_bold, helvetica, arial, sans-serif'\"}}}}}]}}}",
          "filters": "[{\"expression\":{\"Column\":{\"Expression\":{\"SourceRef\":{\"Entity\":\"Municipal-Delitos-2015-2021_dic2021\"}},\"Property\":\"Año\"}},\"filter\":{\"Version\":2,\"From\":[{\"Name\":\"m\",\"Entity\":\"Municipal-Delitos-2015-2021_dic2021\",\"Type\":0}],\"Where\":[{\"Condition\":{\"Comparison\":{\"ComparisonKind\":2,\"Left\":{\"Column\":{\"Expression\":{\"SourceRef\":{\"Source\":\"m\"}},\"Property\":\"Año\"}},\"Right\":{\"Literal\":{\"Value\":\"2018L\"}}}}}]},\"type\":\"Advanced\",\"howCreated\":0,\"isHiddenInViewMode\":false}]",
          "height": 320.00,
          "width": 496.00,
          "x": 16.00,
          "y": 384.00,
          "z": 3000.00
        },
        {
          "config": "{\"name\":\"b22055acd3d8266c19ef\",\"layouts\":[{\"id\":0,\"position\":{\"x\":0,\"y\":0,\"z\":0,\"width\":1280,\"height\":160,\"tabOrder\":9000}}],\"singleVisual\":{\"visualType\":\"basicShape\",\"drillFilterOtherVisuals\":true,\"objects\":{\"general\":[{\"properties\":{\"shapeType\":{\"expr\":{\"Literal\":{\"Value\":\"'rectangle'\"}}}}}],\"line\":[{\"properties\":{\"lineColor\":{\"solid\":{\"color\":{\"expr\":{\"ThemeDataColor\":{\"ColorId\":1,\"Percent\":0}}}}},\"roundEdge\":{\"expr\":{\"Literal\":{\"Value\":\"16L\"}}}}}],\"fill\":[{\"properties\":{\"fillColor\":{\"solid\":{\"color\":{\"expr\":{\"Literal\":{\"Value\":\"'#000000'\"}}}}},\"show\":{\"expr\":{\"Literal\":{\"Value\":\"false\"}}}}}]},\"vcObjects\":{\"border\":[{\"properties\":{\"show\":{\"expr\":{\"Literal\":{\"Value\":\"false\"}}},\"color\":{\"solid\":{\"color\":{\"expr\":{\"ThemeDataColor\":{\"ColorId\":1,\"Percent\":0}}}}},\"radius\":{\"expr\":{\"Literal\":{\"Value\":\"22D\"}}}}}],\"background\":[{\"properties\":{\"show\":{\"expr\":{\"Literal\":{\"Value\":\"false\"}}},\"color\":{\"solid\":{\"color\":{\"expr\":{\"ThemeDataColor\":{\"ColorId\":1,\"Percent\":0}}}}},\"transparency\":{\"expr\":{\"Literal\":{\"Value\":\"49D\"}}}}}],\"visualLink\":[{\"properties\":{\"show\":{\"expr\":{\"Literal\":{\"Value\":\"false\"}}}}}],\"dropShadow\":[{\"properties\":{\"show\":{\"expr\":{\"Literal\":{\"Value\":\"false\"}}},\"preset\":{\"expr\":{\"Literal\":{\"Value\":\"'Center'\"}}},\"position\":{\"expr\":{\"Literal\":{\"Value\":\"'Inner'\"}}},\"color\":{\"solid\":{\"color\":{\"expr\":{\"Literal\":{\"Value\":\"'#666666'\"}}}}},\"transparency\":{\"expr\":{\"Literal\":{\"Value\":\"70L\"}}},\"shadowSpread\":{\"expr\":{\"Literal\":{\"Value\":\"0L\"}}},\"shadowBlur\":{\"expr\":{\"Literal\":{\"Value\":\"20L\"}}},\"angle\":{\"expr\":{\"Literal\":{\"Value\":\"0L\"}}},\"shadowDistance\":{\"expr\":{\"Literal\":{\"Value\":\"0L\"}}}}}],\"stylePreset\":[{\"properties\":{\"name\":{\"expr\":{\"Literal\":{\"Value\":\"'Minimal'\"}}}}}],\"title\":[{\"properties\":{\"show\":{\"expr\":{\"Literal\":{\"Value\":\"false\"}}}}}]}}}",
          "filters": "[]",
          "height": 160.00,
          "width": 1280.00,
          "x": 0.00,
          "y": 0.00,
          "z": 0.00
        },
        {
          "config": "{\"name\":\"c3a0d5671b8db1675dff\",\"layouts\":[{\"id\":0,\"position\":{\"x\":960,\"y\":16,\"z\":4000,\"width\":144,\"height\":64,\"tabOrder\":3000}}],\"singleVisual\":{\"visualType\":\"slicer\",\"projections\":{\"Values\":[{\"queryRef\":\"Municipal-Delitos-2015-2021_dic2021.Tipo de delito\",\"active\":true}]},\"prototypeQuery\":{\"Version\":2,\"From\":[{\"Name\":\"m\",\"Entity\":\"Municipal-Delitos-2015-2021_dic2021\",\"Type\":0}],\"Select\":[{\"Column\":{\"Expression\":{\"SourceRef\":{\"Source\":\"m\"}},\"Property\":\"Tipo de delito\"},\"Name\":\"Municipal-Delitos-2015-2021_dic2021.Tipo de delito\"}]},\"drillFilterOtherVisuals\":true,\"objects\":{\"data\":[{\"properties\":{\"mode\":{\"expr\":{\"Literal\":{\"Value\":\"'Dropdown'\"}}}}}],\"general\":[{\"properties\":{\"outlineColor\":{\"solid\":{\"color\":{\"expr\":{\"ThemeDataColor\":{\"ColorId\":3,\"Percent\":-0.5}}}}},\"orientation\":{\"expr\":{\"Literal\":{\"Value\":\"1D\"}}}}}],\"header\":[{\"properties\":{\"show\":{\"expr\":{\"Literal\":{\"Value\":\"true\"}}},\"fontColor\":{\"solid\":{\"color\":{\"expr\":{\"Literal\":{\"Value\":\"'#070f25'\"}}}}},\"textSize\":{\"expr\":{\"Literal\":{\"Value\":\"9D\"}}},\"fontFamily\":{\"expr\":{\"Literal\":{\"Value\":\"'''Segoe UI Bold'', wf_segoe-ui_bold, helvetica, arial, sans-serif'\"}}},\"outlineStyle\":{\"expr\":{\"Literal\":{\"Value\":\"0L\"}}}}}],\"items\":[{\"properties\":{\"fontColor\":{\"solid\":{\"color\":{\"expr\":{\"ThemeDataColor\":{\"ColorId\":0,\"Percent\":0}}}}},\"background\":{\"solid\":{\"color\":{\"expr\":{\"ThemeDataColor\":{\"ColorId\":3,\"Percent\":-0.5}}}}}}}]},\"vcObjects\":{\"background\":[{\"properties\":{\"show\":{\"expr\":{\"Literal\":{\"Value\":\"false\"}}},\"color\":{\"solid\":{\"color\":{\"expr\":{\"ThemeDataColor\":{\"ColorId\":1,\"Percent\":0}}}}},\"transparency\":{\"expr\":{\"Literal\":{\"Value\":\"49D\"}}}}}],\"border\":[{\"properties\":{\"show\":{\"expr\":{\"Literal\":{\"Value\":\"false\"}}},\"color\":{\"solid\":{\"color\":{\"expr\":{\"ThemeDataColor\":{\"ColorId\":1,\"Percent\":0}}}}},\"radius\":{\"expr\":{\"Literal\":{\"Value\":\"22D\"}}}}}],\"dropShadow\":[{\"properties\":{\"show\":{\"expr\":{\"Literal\":{\"Value\":\"false\"}}},\"preset\":{\"expr\":{\"Literal\":{\"Value\":\"'Center'\"}}},\"position\":{\"expr\":{\"Literal\":{\"Value\":\"'Inner'\"}}},\"color\":{\"solid\":{\"color\":{\"expr\":{\"Literal\":{\"Value\":\"'#666666'\"}}}}},\"transparency\":{\"expr\":{\"Literal\":{\"Value\":\"70L\"}}},\"shadowSpread\":{\"expr\":{\"Literal\":{\"Value\":\"0L\"}}},\"shadowBlur\":{\"expr\":{\"Literal\":{\"Value\":\"20L\"}}},\"angle\":{\"expr\":{\"Literal\":{\"Value\":\"0L\"}}},\"shadowDistance\":{\"expr\":{\"Literal\":{\"Value\":\"0L\"}}}}}],\"stylePreset\":[{\"properties\":{\"name\":{\"expr\":{\"Literal\":{\"Value\":\"'Minimal'\"}}}}}],\"title\":[{\"properties\":{\"show\":{\"expr\":{\"Literal\":{\"Value\":\"false\"}}}}}]}}}",
          "filters": "[]",
          "height": 64.00,
          "width": 144.00,
          "x": 960.00,
          "y": 16.00,
          "z": 4000.00
        },
        {
          "config": "{\"name\":\"c74bab3d947d2d2ded6c\",\"layouts\":[{\"id\":0,\"position\":{\"x\":16,\"y\":160,\"z\":11000,\"width\":496,\"height\":208,\"tabOrder\":11000}}],\"singleVisual\":{\"visualType\":\"pieChart\",\"projections\":{\"Y\":[{\"queryRef\":\"Sum(Municipal-Delitos-2015-2021_dic2021.delitos)\"}],\"Category\":[{\"queryRef\":\"Municipal-Delitos-2015-2021_dic2021.Entidad\",\"active\":true}]},\"prototypeQuery\":{\"Version\":2,\"From\":[{\"Name\":\"m\",\"Entity\":\"Municipal-Delitos-2015-2021_dic2021\",\"Type\":0}],\"Select\":[{\"Aggregation\":{\"Expression\":{\"Column\":{\"Expression\":{\"SourceRef\":{\"Source\":\"m\"}},\"Property\":\"delitos\"}},\"Function\":0},\"Name\":\"Sum(Municipal-Delitos-2015-2021_dic2021.delitos)\"},{\"Column\":{\"Expression\":{\"SourceRef\":{\"Source\":\"m\"}},\"Property\":\"Entidad\"},\"Name\":\"Municipal-Delitos-2015-2021_dic2021.Entidad\"}],\"OrderBy\":[{\"Direction\":2,\"Expression\":{\"Aggregation\":{\"Expression\":{\"Column\":{\"Expression\":{\"SourceRef\":{\"Source\":\"m\"}},\"Property\":\"delitos\"}},\"Function\":0}}}]},\"drillFilterOtherVisuals\":true,\"hasDefaultSort\":true,\"objects\":{\"labels\":[{\"properties\":{\"color\":{\"solid\":{\"color\":{\"expr\":{\"Literal\":{\"Value\":\"'#070f25'\"}}}}},\"fontSize\":{\"expr\":{\"Literal\":{\"Value\":\"11D\"}}},\"labelStyle\":{\"expr\":{\"Literal\":{\"Value\":\"'Category, percent of total'\"}}},\"show\":{\"expr\":{\"Literal\":{\"Value\":\"true\"}}}}}],\"legend\":[{\"properties\":{\"fontSize\":{\"expr\":{\"Literal\":{\"Value\":\"9D\"}}},\"show\":{\"expr\":{\"Literal\":{\"Value\":\"false\"}}}}}]},\"vcObjects\":{\"stylePreset\":[{\"properties\":{\"name\":{\"expr\":{\"Literal\":{\"Value\":\"'BoldHeader'\"}}}}}],\"border\":[{\"properties\":{\"show\":{\"expr\":{\"Literal\":{\"Value\":\"false\"}}},\"color\":{\"solid\":{\"color\":{\"expr\":{\"ThemeDataColor\":{\"ColorId\":1,\"Percent\":0}}}}},\"radius\":{\"expr\":{\"Literal\":{\"Value\":\"22D\"}}}}}],\"background\":[{\"properties\":{\"show\":{\"expr\":{\"Literal\":{\"Value\":\"false\"}}},\"color\":{\"solid\":{\"color\":{\"expr\":{\"Literal\":{\"Value\":\"'#070f25'\"}}}}},\"transparency\":{\"expr\":{\"Literal\":{\"Value\":\"49D\"}}}}}],\"dropShadow\":[{\"properties\":{\"show\":{\"expr\":{\"Literal\":{\"Value\":\"false\"}}},\"preset\":{\"expr\":{\"Literal\":{\"Value\":\"'Center'\"}}},\"position\":{\"expr\":{\"Literal\":{\"Value\":\"'Inner'\"}}},\"color\":{\"solid\":{\"color\":{\"expr\":{\"ThemeDataColor\":{\"ColorId\":0,\"Percent\":-0.6}}}}},\"transparency\":{\"expr\":{\"Literal\":{\"Value\":\"70L\"}}},\"shadowSpread\":{\"expr\":{\"Literal\":{\"Value\":\"0L\"}}},\"shadowBlur\":{\"expr\":{\"Literal\":{\"Value\":\"20L\"}}},\"angle\":{\"expr\":{\"Literal\":{\"Value\":\"0L\"}}},\"shadowDistance\":{\"expr\":{\"Literal\":{\"Value\":\"0L\"}}}}}],\"title\":[{\"properties\":{\"background\":{\"solid\":{\"color\":{\"expr\":{\"Literal\":{\"Value\":\"'#070f25'\"}}}}},\"alignment\":{\"expr\":{\"Literal\":{\"Value\":\"'center'\"}}},\"fontSize\":{\"expr\":{\"Literal\":{\"Value\":\"11D\"}}},\"fontFamily\":{\"expr\":{\"Literal\":{\"Value\":\"'''Segoe UI Bold'', wf_segoe-ui_bold, helvetica, arial, sans-serif'\"}}},\"text\":{\"expr\":{\"Literal\":{\"Value\":\"'Por bien jurídico afectado'\"}}},\"show\":{\"expr\":{\"Literal\":{\"Value\":\"true\"}}},\"fontColor\":{\"solid\":{\"color\":{\"expr\":{\"Literal\":{\"Value\":\"'#ffffff'\"}}}}}}}]}}}",
          "filters": "[{\"expression\":{\"Column\":{\"Expression\":{\"SourceRef\":{\"Entity\":\"Municipal-Delitos-2015-2021_dic2021\"}},\"Property\":\"Año\"}},\"filter\":{\"Version\":2,\"From\":[{\"Name\":\"m\",\"Entity\":\"Municipal-Delitos-2015-2021_dic2021\",\"Type\":0}],\"Where\":[{\"Condition\":{\"Comparison\":{\"ComparisonKind\":2,\"Left\":{\"Column\":{\"Expression\":{\"SourceRef\":{\"Source\":\"m\"}},\"Property\":\"Año\"}},\"Right\":{\"Literal\":{\"Value\":\"2018L\"}}}}}]},\"type\":\"Advanced\",\"howCreated\":1,\"isHiddenInViewMode\":false}]",
          "height": 208.00,
          "width": 496.00,
          "x": 16.00,
          "y": 160.00,
          "z": 11000.00
        },
        {
          "config": "{\"name\":\"fe81d545b3f95c831be7\",\"layouts\":[{\"id\":0,\"position\":{\"x\":1104,\"y\":80,\"z\":6000,\"width\":160,\"height\":64,\"tabOrder\":5000}}],\"singleVisual\":{\"visualType\":\"slicer\",\"projections\":{\"Values\":[{\"queryRef\":\"Municipal-Delitos-2015-2021_dic2021.Municipio\",\"active\":true}]},\"prototypeQuery\":{\"Version\":2,\"From\":[{\"Name\":\"m\",\"Entity\":\"Municipal-Delitos-2015-2021_dic2021\",\"Type\":0}],\"Select\":[{\"Column\":{\"Expression\":{\"SourceRef\":{\"Source\":\"m\"}},\"Property\":\"Municipio\"},\"Name\":\"Municipal-Delitos-2015-2021_dic2021.Municipio\"}]},\"drillFilterOtherVisuals\":true,\"objects\":{\"data\":[{\"properties\":{\"mode\":{\"expr\":{\"Literal\":{\"Value\":\"'Dropdown'\"}}}}}],\"general\":[{\"properties\":{\"outlineColor\":{\"solid\":{\"color\":{\"expr\":{\"ThemeDataColor\":{\"ColorId\":3,\"Percent\":-0.5}}}}},\"orientation\":{\"expr\":{\"Literal\":{\"Value\":\"1D\"}}}}}],\"header\":[{\"properties\":{\"show\":{\"expr\":{\"Literal\":{\"Value\":\"true\"}}},\"fontColor\":{\"solid\":{\"color\":{\"expr\":{\"Literal\":{\"Value\":\"'#070f25'\"}}}}},\"textSize\":{\"expr\":{\"Literal\":{\"Value\":\"9D\"}}},\"fontFamily\":{\"expr\":{\"Literal\":{\"Value\":\"'''Segoe UI Bold'', wf_segoe-ui_bold, helvetica, arial, sans-serif'\"}}},\"outlineStyle\":{\"expr\":{\"Literal\":{\"Value\":\"0L\"}}}}}],\"items\":[{\"properties\":{\"fontColor\":{\"solid\":{\"color\":{\"expr\":{\"ThemeDataColor\":{\"ColorId\":0,\"Percent\":0}}}}},\"background\":{\"solid\":{\"color\":{\"expr\":{\"ThemeDataColor\":{\"ColorId\":3,\"Percent\":-0.5}}}}}}}]},\"vcObjects\":{\"background\":[{\"properties\":{\"show\":{\"expr\":{\"Literal\":{\"Value\":\"false\"}}},\"color\":{\"solid\":{\"color\":{\"expr\":{\"ThemeDataColor\":{\"ColorId\":1,\"Percent\":0}}}}},\"transparency\":{\"expr\":{\"Literal\":{\"Value\":\"49D\"}}}}}],\"border\":[{\"properties\":{\"show\":{\"expr\":{\"Literal\":{\"Value\":\"false\"}}},\"color\":{\"solid\":{\"color\":{\"expr\":{\"ThemeDataColor\":{\"ColorId\":1,\"Percent\":0}}}}},\"radius\":{\"expr\":{\"Literal\":{\"Value\":\"22D\"}}}}}],\"dropShadow\":[{\"properties\":{\"show\":{\"expr\":{\"Literal\":{\"Value\":\"false\"}}},\"preset\":{\"expr\":{\"Literal\":{\"Value\":\"'Center'\"}}},\"position\":{\"expr\":{\"Literal\":{\"Value\":\"'Inner'\"}}},\"color\":{\"solid\":{\"color\":{\"expr\":{\"Literal\":{\"Value\":\"'#666666'\"}}}}},\"transparency\":{\"expr\":{\"Literal\":{\"Value\":\"70L\"}}},\"shadowSpread\":{\"expr\":{\"Literal\":{\"Value\":\"0L\"}}},\"shadowBlur\":{\"expr\":{\"Literal\":{\"Value\":\"20L\"}}},\"angle\":{\"expr\":{\"Literal\":{\"Value\":\"0L\"}}},\"shadowDistance\":{\"expr\":{\"Literal\":{\"Value\":\"0L\"}}}}}],\"stylePreset\":[{\"properties\":{\"name\":{\"expr\":{\"Literal\":{\"Value\":\"'Minimal'\"}}}}}],\"title\":[{\"properties\":{\"show\":{\"expr\":{\"Literal\":{\"Value\":\"false\"}}}}}]}}}",
          "filters": "[]",
          "height": 64.00,
          "width": 160.00,
          "x": 1104.00,
          "y": 80.00,
          "z": 6000.00
        }
      ],
      "width": 1280.00
    }
  ],
  "theme": "Frontier"
}